projects/reg8/rtl/reg8.v
// reg8.v
// 8-bit registered with synchronous load and active-low reset.
//
// Ports:
//   clk    - clock input
//   rst_n  - active-low synchronous reset
//   en     - load enable (1 = load d into q, 0 = hold q)
//   d      - 8-bit data input
//   q      - 8-bit registered output
//
// Behavior:
//   On every rising edge of clk:
//     If rst_n == 0  ->  q <= 0
//     Else if en == 1 ->  q <= d
//     Else            ->  q holds current value
//
// This module is the Phase 2 bring-up DUT.
// It is intentionally simple so the focus stays on the validation harness.

`timescale 1ns/1ps

module reg8 (
    input  wire       clk,
    input  wire       rst_n,
    input  wire       en,
    input  wire [7:0] d,
    output reg  [7:0] q
);

    always @(posedge clk) begin
        if (!rst_n)
            q <= 8'h00;
        else if (en)
            q <= d;
        // else: q holds its current value (implicit register behaviour)
    end

endmodule

sim/cocotb/dump.vcd
$version Generated by VerilatedVcd $end
$timescale 1ps $end
 $scope module $rootio $end
  $var wire 1 # clk $end
  $var wire 1 $ rst_n $end
  $var wire 1 % en $end
  $var wire 8 & d [7:0] $end
  $var wire 8 ' q [7:0] $end
 $upscope $end
 $scope module reg8 $end
  $var wire 1 ( clk $end
  $var wire 1 ) rst_n $end
  $var wire 1 * en $end
  $var wire 8 + d [7:0] $end
  $var wire 8 , q [7:0] $end
 $upscope $end
$enddefinitions $end


#0
1#
0$
0%
b00000000 &
b00000000 '
1(
0)
0*
b00000000 +
b00000000 ,
#5000
0#
0(
#10000
1#
1(
#15000
0#
0(
#20000
1#
1(
#25000
0#
1$
0(
1)
#25001
1%
b10101011 &
1*
b10101011 +
#30000
1#
b10101011 '
1(
b10101011 ,
#35000
0#
0$
0(
0)
#40000
1#
b00000000 '
1(
b00000000 ,
#40001
0%
b00000000 &
0*
b00000000 +
#45001
0#
0(
#50001
1#
1(
#55001
0#
0(
#60001
1#
1(
#65001
0#
0(
#70001
1#
1(
#75001
0#
1$
0(
1)
#75002
1%
b00000001 &
1*
b00000001 +
#80001
1#
b00000001 '
1(
b00000001 ,
#85001
0#
b01111111 &
0(
b01111111 +
#90001
1#
b01111111 '
1(
b01111111 ,
#95001
0#
b10000000 &
0(
b10000000 +
#100001
1#
b10000000 '
1(
b10000000 ,
#105001
0#
b11111111 &
0(
b11111111 +
#110001
1#
b11111111 '
1(
b11111111 ,
#115001
0#
b10100101 &
0(
b10100101 +
#120001
1#
b10100101 '
1(
b10100101 ,
#125001
0#
b01011010 &
0(
b01011010 +
#130001
1#
b01011010 '
1(
b01011010 ,
#135001
0#
b00000000 &
0(
b00000000 +
#140001
1#
b00000000 '
1(
b00000000 ,
#145001
0#
0(
#145002
1#
0$
0%
1(
0)
0*
#150002
0#
0(
#155002
1#
1(
#160002
0#
0(
#165002
1#
1(
#170002
0#
1$
0(
1)
#170003
1%
b01000010 &
1*
b01000010 +
#175002
1#
b01000010 '
1(
b01000010 ,
#180002
0#
0%
b00000000 &
0(
0*
b00000000 +
#185002
1#
1(
#190002
0#
b11111111 &
0(
b11111111 +
#195002
1#
1(
#200002
0#
b00010001 &
0(
b00010001 +
#205002
1#
1(
#210002
0#
b10011001 &
0(
b10011001 +
#215002
1#
1(
#220002
0#
0(
#220003
1#
0$
b00000000 &
b00000000 '
1(
0)
b00000000 +
b00000000 ,
#225003
0#
0(
#230003
1#
1(
#235003
0#
0(
#240003
1#
1(
#245003
0#
1$
0(
1)
#250003
1#
1(
#255003
0#
0$
1%
b11111111 &
0(
0)
1*
b11111111 +
