projects/periph_ctrl/rtl/periph_ctrl.v
// periph_ctrl.v
// A simple register-mapped peripheral controller.
//
// This is the Phase 3 MVP DUT.  It is representative of the kind of
// memory-mapped peripheral block found on real FPGAs and SoCs:
// a small address-decoded register file with read-only, read-write,
// and status registers, a GPIO output, and clean error signaling.
//
// Register map  (addr[2:0]):
// ┌──────┬────────────┬────────┬───────┬────────────────────────────────┐
// │ Addr │ Name       │ Access │ Reset │ Description                    │
// ├──────┼────────────┼────────┼───────┼────────────────────────────────┤
// │ 0x0  │ REG_ID     │ RO     │ 0xAB  │ Peripheral ID constant         │
// │ 0x1  │ REG_GPIO   │ RW     │ 0x00  │ GPIO output register           │
// │ 0x2  │ REG_CTRL   │ RW     │ 0x00  │ Control register               │
// │ 0x3  │ REG_STATUS │ RO     │ –     │ {6'b0, ctrl_en, gpio_nonzero} │
// │ 0x4+ │ –          │ –      │ –     │ Invalid — asserts addr_err     │
// └──────┴────────────┴────────┴───────┴────────────────────────────────┘
//
// REG_STATUS fields:
//   bit 0 : gpio_nonzero — 1 if any GPIO output bit is high
//   bit 1 : ctrl_en      — mirrors bit 0 of REG_CTRL
//   bits 7:2 : reserved, always 0
//
// Timing:
//   All outputs (rd_data, rd_valid, addr_err) are registered.
//   They update on the rising edge following a valid rd_en or wr_en pulse.
//   addr_err pulses for exactly one cycle on an invalid-address access.
//
// Writes to read-only registers (REG_ID, REG_STATUS) are silently ignored.

`timescale 1ns/1ps

module periph_ctrl (
    input  wire       clk,
    input  wire       rst_n,

    // Register bus
    input  wire [2:0] addr,       // register address (0-3 valid, 4-7 invalid)
    input  wire       wr_en,      // write enable (pulse high for one cycle)
    input  wire       rd_en,      // read enable  (pulse high for one cycle)
    input  wire [7:0] wr_data,    // write data

    output reg  [7:0] rd_data,    // read data (valid when rd_valid=1)
    output reg        rd_valid,   // 1 for the cycle after a valid read
    output reg        addr_err,   // 1 for the cycle after an invalid address

    // GPIO
    output wire [7:0] gpio_out    // live value of REG_GPIO
);

    // -----------------------------------------------------------------------
    // Address constants
    // -----------------------------------------------------------------------
    localparam [2:0] ADDR_ID     = 3'h0;
    localparam [2:0] ADDR_GPIO   = 3'h1;
    localparam [2:0] ADDR_CTRL   = 3'h2;
    localparam [2:0] ADDR_STATUS = 3'h3;
    localparam [7:0] PERIPHERAL_ID = 8'hAB;

    // -----------------------------------------------------------------------
    // Internal registers
    // -----------------------------------------------------------------------
    reg [7:0] reg_gpio;   // RW: drives gpio_out
    reg [7:0] reg_ctrl;   // RW: general control bits

    // -----------------------------------------------------------------------
    // Combinational derived signals
    // -----------------------------------------------------------------------
    wire addr_valid  = (addr <= 3'h3);

    // REG_STATUS is computed from current register state, not stored
    wire [7:0] reg_status = {6'b00_0000, reg_ctrl[0], |reg_gpio};

    // GPIO output is the live register value (no extra latency)
    assign gpio_out = reg_gpio;

    // -----------------------------------------------------------------------
    // Write path  (synchronous, active-low reset)
    // Writes to RO registers are silently ignored — standard peripheral behavior.
    // -----------------------------------------------------------------------
    always @(posedge clk) begin
        if (!rst_n) begin
            reg_gpio <= 8'h00;
            reg_ctrl <= 8'h00;
        end else if (wr_en && addr_valid) begin
            case (addr)
                ADDR_GPIO:   reg_gpio <= wr_data;
                ADDR_CTRL:   reg_ctrl <= wr_data;
                default: ;   // ADDR_ID and ADDR_STATUS: writes silently ignored
            endcase
        end
    end

    // -----------------------------------------------------------------------
    // Read path + error signaling  (synchronous)
    // rd_valid and addr_err are mutually exclusive; both clear when idle.
    // -----------------------------------------------------------------------
    always @(posedge clk) begin
        if (!rst_n) begin
            rd_data  <= 8'h00;
            rd_valid <= 1'b0;
            addr_err <= 1'b0;
        end else begin
            // Default: clear strobes each cycle (pulsed, not sticky)
            rd_valid <= 1'b0;
            addr_err <= 1'b0;

            if (rd_en || wr_en) begin
                if (!addr_valid) begin
                    // Invalid address on any access type
                    addr_err <= 1'b1;
                end else if (rd_en) begin
                    // Valid read
                    rd_valid <= 1'b1;
                    case (addr)
                        ADDR_ID:     rd_data <= PERIPHERAL_ID;
                        ADDR_GPIO:   rd_data <= reg_gpio;
                        ADDR_CTRL:   rd_data <= reg_ctrl;
                        ADDR_STATUS: rd_data <= reg_status;
                        default:     rd_data <= 8'hFF; // unreachable
                    endcase
                end
                // wr_en with valid addr: write happens silently, no rd_valid
            end
        end
    end

endmodule

projects/periph_ctrl/sim/dump.vcd
$version Generated by VerilatedVcd $end
$timescale 1ps $end
 $scope module $rootio $end
  $var wire 1 # clk $end
  $var wire 1 $ rst_n $end
  $var wire 3 % addr [2:0] $end
  $var wire 1 & wr_en $end
  $var wire 1 ' rd_en $end
  $var wire 8 ( wr_data [7:0] $end
  $var wire 8 ) rd_data [7:0] $end
  $var wire 1 * rd_valid $end
  $var wire 1 + addr_err $end
  $var wire 8 , gpio_out [7:0] $end
 $upscope $end
 $scope module periph_ctrl $end
  $var wire 1 - clk $end
  $var wire 1 . rst_n $end
  $var wire 3 / addr [2:0] $end
  $var wire 1 0 wr_en $end
  $var wire 1 1 rd_en $end
  $var wire 8 2 wr_data [7:0] $end
  $var wire 8 3 rd_data [7:0] $end
  $var wire 1 4 rd_valid $end
  $var wire 1 5 addr_err $end
  $var wire 8 6 gpio_out [7:0] $end
  $var wire 3 ; ADDR_ID [2:0] $end
  $var wire 3 < ADDR_GPIO [2:0] $end
  $var wire 3 = ADDR_CTRL [2:0] $end
  $var wire 3 > ADDR_STATUS [2:0] $end
  $var wire 8 ? PERIPHERAL_ID [7:0] $end
  $var wire 8 7 reg_gpio [7:0] $end
  $var wire 8 8 reg_ctrl [7:0] $end
  $var wire 1 9 addr_valid $end
  $var wire 8 : reg_status [7:0] $end
 $upscope $end
$enddefinitions $end


#0
1#
0$
b000 %
0&
0'
b00000000 (
b00000000 )
0*
0+
b00000000 ,
1-
0.
b000 /
00
01
b00000000 2
b00000000 3
04
05
b00000000 6
b00000000 7
b00000000 8
19
b00000000 :
b000 ;
b001 <
b010 =
b011 >
b10101011 ?
#5000
0#
0-
#10000
1#
1-
#15000
0#
0-
#20000
1#
1-
#25000
0#
1$
1'
0-
1.
11
#30000
1#
b10101011 )
1*
1-
b10101011 3
14
#35000
0#
b001 %
0-
b001 /
#40000
1#
b00000000 )
1-
b00000000 3
#45000
0#
b010 %
0-
b010 /
#50000
1#
1-
#55000
0#
b011 %
0-
b011 /
#60000
1#
1-
#65000
0#
0'
0-
01
#65001
1#
0$
b000 %
0*
1-
0.
b000 /
04
#70001
0#
0-
#75001
1#
1-
#80001
0#
0-
#85001
1#
1-
#90001
0#
1$
b001 %
1&
b01010101 (
0-
1.
b001 /
10
b01010101 2
#95001
1#
b01010101 ,
1-
b01010101 6
b01010101 7
b00000001 :
#100001
0#
0&
1'
b00000000 (
0-
00
11
b00000000 2
#105001
1#
b01010101 )
1*
1-
b01010101 3
14
#110001
0#
1&
0'
b11111111 (
0-
10
01
b11111111 2
#115001
1#
0*
b11111111 ,
1-
04
b11111111 6
b11111111 7
#120001
0#
0&
1'
b00000000 (
0-
00
11
b00000000 2
#125001
1#
b11111111 )
1*
1-
b11111111 3
14
#130001
0#
1&
0'
0-
10
01
#135001
1#
0*
b00000000 ,
1-
04
b00000000 6
b00000000 7
b00000000 :
#140001
0#
0&
1'
0-
00
11
#145001
1#
b00000000 )
1*
1-
b00000000 3
14
#150001
0#
b010 %
1&
0'
b00000001 (
0-
b010 /
10
01
b00000001 2
#155001
1#
0*
1-
04
b00000001 8
b00000010 :
#160001
0#
0&
1'
b00000000 (
0-
00
11
b00000000 2
#165001
1#
b00000001 )
1*
1-
b00000001 3
14
#170001
0#
1&
0'
b10100101 (
0-
10
01
b10100101 2
#175001
1#
0*
1-
04
b10100101 8
#180001
0#
0&
1'
b00000000 (
0-
00
11
b00000000 2
#185001
1#
b10100101 )
1*
1-
b10100101 3
14
#190001
0#
1&
0'
0-
10
01
#195001
1#
0*
1-
04
b00000000 8
b00000000 :
#200001
0#
0&
1'
0-
00
11
#205001
1#
b00000000 )
1*
1-
b00000000 3
14
#210001
0#
0'
0-
01
#210002
1#
0$
b000 %
0*
1-
0.
b000 /
04
#215002
0#
0-
#220002
1#
1-
#225002
0#
0-
#230002
1#
1-
#235002
0#
1$
b001 %
1&
b00000001 (
0-
1.
b001 /
10
b00000001 2
#240002
1#
b00000001 ,
1-
b00000001 6
b00000001 7
b00000001 :
#245002
0#
b10000000 (
0-
b10000000 2
#250002
1#
b10000000 ,
1-
b10000000 6
b10000000 7
#255002
0#
b11111111 (
0-
b11111111 2
#260002
1#
b11111111 ,
1-
b11111111 6
b11111111 7
#265002
0#
b10100101 (
0-
b10100101 2
#270002
1#
b10100101 ,
1-
b10100101 6
b10100101 7
#275002
0#
b01011010 (
0-
b01011010 2
#280002
1#
b01011010 ,
1-
b01011010 6
b01011010 7
#285002
0#
b00000000 (
0-
b00000000 2
#290002
1#
b00000000 ,
1-
b00000000 6
b00000000 7
b00000000 :
#295002
0#
0&
0-
00
#295003
1#
0$
b000 %
1-
0.
b000 /
#300003
0#
0-
#305003
1#
1-
#310003
0#
0-
#315003
1#
1-
#320003
0#
1$
1&
0-
1.
10
#325003
1#
1-
#330003
0#
0&
1'
0-
00
11
#335003
1#
b10101011 )
1*
1-
b10101011 3
14
#340003
0#
0'
0-
01
#340004
1#
0$
b00000000 )
0*
1-
0.
b00000000 3
04
#345004
0#
0-
#350004
1#
1-
#355004
0#
0-
#360004
1#
1-
#365004
0#
1$
b011 %
1'
0-
1.
b011 /
11
#370004
1#
1*
1-
14
#375004
0#
b001 %
1&
0'
b00000001 (
0-
b001 /
10
01
b00000001 2
#380004
1#
0*
b00000001 ,
1-
04
b00000001 6
b00000001 7
b00000001 :
#385004
0#
b011 %
0&
1'
b00000000 (
0-
b011 /
00
11
b00000000 2
#390004
1#
b00000001 )
1*
1-
b00000001 3
14
#395004
0#
b010 %
1&
0'
b00000001 (
0-
b010 /
10
01
b00000001 2
#400004
1#
0*
1-
04
b00000001 8
b00000011 :
#405004
0#
b011 %
0&
1'
b00000000 (
0-
b011 /
00
11
b00000000 2
#410004
1#
b00000011 )
1*
1-
b00000011 3
14
#415004
0#
b010 %
1&
0'
0-
b010 /
10
01
#420004
1#
0*
1-
04
b00000000 8
b00000001 :
#425004
0#
b011 %
0&
1'
0-
b011 /
00
11
#430004
1#
b00000001 )
1*
1-
b00000001 3
14
#435004
0#
b001 %
1&
0'
0-
b001 /
10
01
#440004
1#
0*
b00000000 ,
1-
04
b00000000 6
b00000000 7
b00000000 :
#445004
0#
b011 %
0&
1'
0-
b011 /
00
11
#450004
1#
b00000000 )
1*
1-
b00000000 3
14
#455004
0#
0'
0-
01
#455005
1#
0$
b000 %
0*
1-
0.
b000 /
04
#460005
0#
0-
#465005
1#
1-
#470005
0#
0-
#475005
1#
1-
#480005
0#
1$
b100 %
1'
0-
1.
b100 /
11
09
#485005
1#
1+
1-
15
#490005
0#
1&
0'
b11111111 (
0-
10
01
b11111111 2
#495005
1#
1-
#500005
0#
b101 %
0&
1'
b00000000 (
0-
b101 /
00
11
b00000000 2
#505005
1#
1-
#510005
0#
1&
0'
b11111111 (
0-
10
01
b11111111 2
#515005
1#
1-
#520005
0#
b110 %
0&
1'
b00000000 (
0-
b110 /
00
11
b00000000 2
#525005
1#
1-
#530005
0#
1&
0'
b11111111 (
0-
10
01
b11111111 2
#535005
1#
1-
#540005
0#
b111 %
0&
1'
b00000000 (
0-
b111 /
00
11
b00000000 2
#545005
1#
1-
#550005
0#
1&
0'
b11111111 (
0-
10
01
b11111111 2
#555005
1#
1-
#560005
0#
0&
0-
00
#560006
1#
0$
b000 %
b00000000 (
0+
1-
0.
b000 /
b00000000 2
05
19
#565006
0#
0-
#570006
1#
1-
#575006
0#
0-
#580006
1#
1-
#585006
0#
1$
1'
0-
1.
11
#590006
1#
b10101011 )
1*
1-
b10101011 3
14
#595006
0#
b001 %
1&
0'
b00000001 (
0-
b001 /
10
01
b00000001 2
#600006
1#
0*
b00000001 ,
1-
04
b00000001 6
b00000001 7
b00000001 :
#605006
0#
b00000010 (
0-
b00000010 2
#610006
1#
b00000010 ,
1-
b00000010 6
b00000010 7
#615006
0#
b00000100 (
0-
b00000100 2
#620006
1#
b00000100 ,
1-
b00000100 6
b00000100 7
#625006
0#
b00001000 (
0-
b00001000 2
#630006
1#
b00001000 ,
1-
b00001000 6
b00001000 7
#635006
0#
b00010000 (
0-
b00010000 2
#640006
1#
b00010000 ,
1-
b00010000 6
b00010000 7
#645006
0#
b00100000 (
0-
b00100000 2
#650006
1#
b00100000 ,
1-
b00100000 6
b00100000 7
#655006
0#
b01000000 (
0-
b01000000 2
#660006
1#
b01000000 ,
1-
b01000000 6
b01000000 7
#665006
0#
b10000000 (
0-
b10000000 2
#670006
1#
b10000000 ,
1-
b10000000 6
b10000000 7
#675006
0#
b010 %
b00000001 (
0-
b010 /
b00000001 2
#680006
1#
1-
b00000001 8
b00000011 :
#685006
0#
b001 %
b11110000 (
0-
b001 /
b11110000 2
#690006
1#
b11110000 ,
1-
b11110000 6
b11110000 7
#695006
0#
b011 %
0&
1'
b00000000 (
0-
b011 /
00
11
b00000000 2
#700006
1#
b00000011 )
1*
1-
b00000011 3
14
#705006
0#
b000 %
1&
0'
b11011110 (
0-
b000 /
10
01
b11011110 2
#710006
1#
0*
1-
04
#715006
0#
b011 %
b10101101 (
0-
b011 /
b10101101 2
#720006
1#
1-
#725006
0#
b000 %
0&
1'
b00000000 (
0-
b000 /
00
11
b00000000 2
#730006
1#
b10101011 )
1*
1-
b10101011 3
14
#735006
0#
b001 %
1&
0'
b01000010 (
0-
b001 /
10
01
b01000010 2
#740006
1#
0*
b01000010 ,
1-
04
b01000010 6
b01000010 7
#745006
0#
b010 %
b00000000 (
0-
b010 /
b00000000 2
#750006
1#
1-
b00000000 8
b00000001 :
#755006
0#
b001 %
0&
1'
0-
b001 /
00
11
#760006
1#
b01000010 )
1*
1-
b01000010 3
14
#765006
0#
b010 %
0-
b010 /
#770006
1#
b00000000 )
1-
b00000000 3
#775006
0#
b101 %
0-
b101 /
09
#780006
1#
0*
1+
1-
04
15
#785006
0#
b001 %
0-
b001 /
19
#790006
1#
b01000010 )
1*
0+
1-
b01000010 3
14
05
#795006
0#
0'
0-
01
